jupyterlab_file_browser_sorting_extension/__init__.py
jupyterlab_file_browser_sorting_extension/_version.py
jupyterlab_file_browser_sorting_extension-1.0.14.data/data/share/jupyter/labextensions/jupyterlab_file_browser_sorting_extension/package.json
jupyterlab_file_browser_sorting_extension-1.0.14.data/data/share/jupyter/labextensions/jupyterlab_file_browser_sorting_extension/schemas/jupyterlab_file_browser_sorting_extension/package.json.orig
jupyterlab_file_browser_sorting_extension-1.0.14.data/data/share/jupyter/labextensions/jupyterlab_file_browser_sorting_extension/schemas/jupyterlab_file_browser_sorting_extension/plugin.json
jupyterlab_file_browser_sorting_extension-1.0.14.data/data/share/jupyter/labextensions/jupyterlab_file_browser_sorting_extension/static/509.60f8f6518af8e9aa9ecc.js
jupyterlab_file_browser_sorting_extension-1.0.14.data/data/share/jupyter/labextensions/jupyterlab_file_browser_sorting_extension/static/728.a6ed362485715e83fa87.js
jupyterlab_file_browser_sorting_extension-1.0.14.data/data/share/jupyter/labextensions/jupyterlab_file_browser_sorting_extension/static/remoteEntry.13076dc39e97492b423d.js
jupyterlab_file_browser_sorting_extension-1.0.14.data/data/share/jupyter/labextensions/jupyterlab_file_browser_sorting_extension/static/style.js
jupyterlab_file_browser_sorting_extension-1.0.14.data/data/share/jupyter/labextensions/jupyterlab_file_browser_sorting_extension/static/third-party-licenses.json
jupyterlab_file_browser_sorting_extension-1.0.14.data/data/share/jupyter/labextensions/jupyterlab_file_browser_sorting_extension/install.json
jupyterlab_file_browser_sorting_extension-1.0.14.dist-info/METADATA
jupyterlab_file_browser_sorting_extension-1.0.14.dist-info/WHEEL
jupyterlab_file_browser_sorting_extension-1.0.14.dist-info/licenses/LICENSE
jupyterlab_file_browser_sorting_extension-1.0.14.dist-info/RECORD
